dissect/etl/__init__.py
dissect/etl/c_etl.py
dissect/etl/etl.py
dissect/etl/exceptions.py
dissect/etl/manifest.py
dissect/etl/utils.py
dissect/etl/headers/__init__.py
dissect/etl/headers/event.py
dissect/etl/headers/headers.py
dissect/etl/headers/logfile.py
dissect/etl/headers/system.py
dissect/etl/headers/utils.py
dissect/etl/manifests/__init__.py
dissect/etl/manifests/xml/{0063715b-eeda-4007-9429-ad526f62696e}.xml
dissect/etl/manifests/xml/{00b7e1df-b469-4c69-9c41-53a6576e3dad}.xml
dissect/etl/manifests/xml/{01090065-b467-4503-9b28-533766761087}.xml
dissect/etl/manifests/xml/{01578f96-c270-4602-ade0-578d9c29fc0c}.xml
dissect/etl/manifests/xml/{017247f2-7e96-11dc-8314-0800200c9a66}.xml
dissect/etl/manifests/xml/{017ba13c-9a55-4f1f-8200-323055aac810}.xml
dissect/etl/manifests/xml/{01853a65-418f-4f36-aefc-dc0f1d2fd235}.xml
dissect/etl/manifests/xml/{01979c6a-42fa-414c-b8aa-eee2c8202018}.xml
dissect/etl/manifests/xml/{02012a8a-adf5-4fab-92cb-ccb7bb3e689a}.xml
dissect/etl/manifests/xml/{0268a8b6-74fd-4302-9dd0-6e8f1795c0cf}.xml
dissect/etl/manifests/xml/{030f2f57-abd0-4427-bcf1-3a3587d7dc7d}.xml
dissect/etl/manifests/xml/{04268430-d489-424d-b914-0cff741d6684}.xml
dissect/etl/manifests/xml/{04a490d4-84c6-4920-9c22-51c80825ff2c}.xml
dissect/etl/manifests/xml/{04d66358-c4a1-419b-8023-23b73902de2c}.xml
dissect/etl/manifests/xml/{05921578-2261-42c7-a0d3-26ddbce6c50d}.xml
dissect/etl/manifests/xml/{059c3e04-5535-4929-85e1-93030e78f47b}.xml
dissect/etl/manifests/xml/{059f0f37-910e-4ff0-a7ee-ae8d49dd319b}.xml
dissect/etl/manifests/xml/{05d7b0f0-2121-4eff-bf6b-ed3f69b894d7}.xml
dissect/etl/manifests/xml/{05f02597-fe85-4e67-8542-69567ab8fd4f}.xml
dissect/etl/manifests/xml/{06184c97-5201-480e-92af-3a3626c5b140}.xml
dissect/etl/manifests/xml/{0657adc1-9ae8-4e18-932d-e6079cda5ab3}.xml
dissect/etl/manifests/xml/{06edcfeb-0fd0-4e53-acca-a6f8bbf81bcb}.xml
dissect/etl/manifests/xml/{07de7879-1c96-41ce-afbd-c659a0e8e643}.xml
dissect_etl-3.13.dist-info/licenses/COPYRIGHT
dissect_etl-3.13.dist-info/licenses/LICENSE
dissect_etl-3.13.dist-info/METADATA
dissect_etl-3.13.dist-info/WHEEL
dissect_etl-3.13.dist-info/top_level.txt
dissect_etl-3.13.dist-info/RECORD
